odoo/addons/sm_partago_user_rest_api/__init__.py
odoo/addons/sm_partago_user_rest_api/__manifest__.py
odoo/addons/sm_partago_user_rest_api/models/__init__.py
odoo/addons/sm_partago_user_rest_api/models/models_carsharing_update_data.py
odoo/addons/sm_partago_user_rest_api/models/models_carsharing_user_request.py
odoo/addons/sm_partago_user_rest_api/models/models_smp_carsharing_registration_request.py
odoo/addons/sm_partago_user_rest_api/services/__init__.py
odoo/addons/sm_partago_user_rest_api/services/schemas.py
odoo/addons/sm_partago_user_rest_api/services/services_cs_registration_request.py
odoo/addons/sm_partago_user_rest_api/services/services_cs_update_data.py
odoo/addons/sm_partago_user_rest_api/services/services_cs_user_request.py
odoo12_addon_sm_partago_user_rest_api-12.0.0.0.7.dist-info/METADATA
odoo12_addon_sm_partago_user_rest_api-12.0.0.0.7.dist-info/WHEEL
odoo12_addon_sm_partago_user_rest_api-12.0.0.0.7.dist-info/top_level.txt
odoo12_addon_sm_partago_user_rest_api-12.0.0.0.7.dist-info/RECORD
