Metadata-Version: 2.1
Name: odoo12-addon-sm-partago-user-rest-api
Version: 12.0.0.0.7
Summary: Enhace EMC subscription request with carsharing logic
Home-page: https://www.sommobilitat.coop
Author: Som Mobilitat
License: UNKNOWN
Platform: UNKNOWN
Classifier: Programming Language :: Python
Classifier: Framework :: Odoo
Classifier: Framework :: Odoo :: 12.0
Requires-Python: >=3.5
Requires-Dist: odoo12-addon-easy-my-coop-api
Requires-Dist: odoo12-addon-sm-partago-user
Requires-Dist: odoo (<12.1dev,>=12.0a)
